imap_processing/__init__.py
imap_processing/_version.py
imap_processing/ancillary/__init__.py
imap_processing/ancillary/ancillary_dataset_combiner.py
imap_processing/ccsds/__init__.py
imap_processing/ccsds/ccsds_data.py
imap_processing/ccsds/excel_to_xtce.py
imap_processing/cdf/__init__.py
imap_processing/cdf/config/imap_codice_global_cdf_attrs.yaml
imap_processing/cdf/config/imap_codice_l1a_variable_attrs.yaml
imap_processing/cdf/config/imap_codice_l2-hi-direct-events_variable_attrs.yaml
imap_processing/cdf/config/imap_codice_l2-hi-omni_variable_attrs.yaml
imap_processing/cdf/config/imap_codice_l2-hi-sectored_variable_attrs.yaml
imap_processing/cdf/config/imap_codice_l2-lo-angular_variable_attrs.yaml
imap_processing/cdf/config/imap_codice_l2-lo-direct-events_variable_attrs.yaml
imap_processing/cdf/config/imap_codice_l2-lo-species_variable_attrs.yaml
imap_processing/cdf/config/imap_constant_attrs.yaml
imap_processing/cdf/config/imap_default_global_cdf_attrs.yaml
imap_processing/cdf/config/imap_enamaps_l2-common_variable_attrs.yaml
imap_processing/cdf/config/imap_enamaps_l2-healpix_variable_attrs.yaml
imap_processing/cdf/config/imap_enamaps_l2-rectangular_variable_attrs.yaml
imap_processing/cdf/config/imap_glows_global_cdf_attrs.yaml
imap_processing/cdf/config/imap_glows_l1a_variable_attrs.yaml
imap_processing/cdf/config/imap_glows_l1b_variable_attrs.yaml
imap_processing/cdf/config/imap_glows_l2_variable_attrs.yaml
imap_processing/cdf/config/imap_hi_global_cdf_attrs.yaml
imap_processing/cdf/config/imap_hi_variable_attrs.yaml
imap_processing/cdf/config/imap_hit_global_cdf_attrs.yaml
imap_processing/cdf/config/imap_hit_l1a_variable_attrs.yaml
imap_processing/cdf/config/imap_hit_l1b_variable_attrs.yaml
imap_processing/cdf/config/imap_hit_l2_variable_attrs.yaml
imap_processing/cdf/config/imap_ialirt_global_cdf_attrs.yaml
imap_processing/cdf/config/imap_ialirt_l1_variable_attrs.yaml
imap_processing/cdf/config/imap_idex_global_cdf_attrs.yaml
imap_processing-1.0.15.dist-info/LICENSE
imap_processing-1.0.15.dist-info/METADATA
imap_processing-1.0.15.dist-info/WHEEL
imap_processing-1.0.15.dist-info/entry_points.txt
imap_processing-1.0.15.dist-info/RECORD
