Metadata-Version: 2.1
Name: imap-processing
Version: 1.0.15
Summary: IMAP Science Operations Center Processing
License: MIT
Keywords: IMAP,SDC,SOC,Science Operations
Author: IMAP SDC Developers
Author-email: imap-sdc@lists.lasp.colorado.edu
Requires-Python: >=3.10,<4
Classifier: Development Status :: 3 - Alpha
Classifier: Intended Audience :: Developers
Classifier: License :: OSI Approved :: MIT License
Classifier: Natural Language :: English
Classifier: Operating System :: MacOS
Classifier: Operating System :: Microsoft :: Windows
Classifier: Operating System :: POSIX
Classifier: Operating System :: Unix
Classifier: Programming Language :: Python :: 3
Classifier: Programming Language :: Python :: 3.10
Classifier: Programming Language :: Python :: 3.11
Classifier: Programming Language :: Python :: 3.12
Classifier: Programming Language :: Python :: 3.13
Classifier: Topic :: Scientific/Engineering
Classifier: Topic :: Software Development
Provides-Extra: dev
Provides-Extra: doc
Provides-Extra: map-visualization
Provides-Extra: test
Provides-Extra: tools
Requires-Dist: astropy-healpix (>=1.0)
Requires-Dist: cdflib (>=1.3.6,<2.0.0)
Requires-Dist: healpy (>=1.18.0,<2.0.0) ; extra == "map-visualization"
Requires-Dist: imap-data-access (>=0.37.0)
Requires-Dist: mypy (==1.10.1) ; extra == "dev"
Requires-Dist: netcdf4 (>=1.7.2,<2.0.0) ; extra == "test"
Requires-Dist: numpy (<=3)
Requires-Dist: numpydoc (>=1.5.0,<2.0.0) ; extra == "doc"
Requires-Dist: openpyxl (>=3.0.7) ; extra == "test" or extra == "tools"
Requires-Dist: pandas (>=2.0.0) ; extra == "tools"
Requires-Dist: pre-commit (>=3.3.3,<4.0.0) ; extra == "dev"
Requires-Dist: pydata-sphinx-theme ; extra == "doc"
Requires-Dist: pytest (>=6.2.5) ; extra == "test"
Requires-Dist: pytest-cov (>=4.0.0,<5.0.0) ; extra == "test"
Requires-Dist: pytest-xdist (>=3.2,<4.0) ; extra == "test"
Requires-Dist: requests (>=2.32.3,<3.0.0) ; extra == "test"
Requires-Dist: ruff (==0.2.1) ; extra == "dev"
Requires-Dist: sammi-cdf (>=1.0,<2.0)
Requires-Dist: scipy (>=1.13,<2.0)
Requires-Dist: space_packet_parser (>=6.0.0)
Requires-Dist: sphinx ; extra == "doc"
Requires-Dist: sphinxcontrib-openapi (>=0.8.3,<0.9.0) ; extra == "doc"
Requires-Dist: spiceypy (>=6.0.0)
Requires-Dist: xarray (>=2024.10.0)
